neogiinstruments/MaiTai/MaiTai_MaiTai.py
neogiinstruments/MaiTai/MaiTai_software.py
neogiinstruments/Photodiode/Photodiode_Photodiode.py
neogiinstruments/Photodiode/Photodiode_Software.py
neogiinstruments/PowerMeter/PowerMeter_PowerMeter.py
neogiinstruments/PowerMeter/PowerMeter_software.py
neogiinstruments/StellarNet.py
neogiinstruments/__init__.py
neogiinstruments/camera/camera_pyvcam.py
neogiinstruments/camera/camera_software.py
neogiinstruments/esp300.py
neogiinstruments/generic_base.py
neogiinstruments/instrumenttype.py
neogiinstruments/ports.py
neogiinstruments/rotator/rotator_K10CR1.py
neogiinstruments/rotator/rotator_elliptec.py
neogiinstruments/rotator/rotator_software.py
neogiinstruments/shutter.py
neogiinstruments-2.6.1.dist-info/entry_points.txt
neogiinstruments-2.6.1.dist-info/LICENSE
neogiinstruments-2.6.1.dist-info/WHEEL
neogiinstruments-2.6.1.dist-info/METADATA
neogiinstruments-2.6.1.dist-info/RECORD
