Metadata-Version: 2.1
Name: neogiinstruments
Version: 2.6.1
Summary: Communication and helper functions for lab equipment
License: MIT
Author: UNT Neogi Lab
Author-email: BrianSquires@my.unt.edu
Requires-Python: >=3.9,<3.10
Classifier: License :: OSI Approved :: MIT License
Classifier: Programming Language :: Python :: 3
Classifier: Programming Language :: Python :: 3.9
Requires-Dist: Instrumental-lib (>=0.6,<0.7)
Requires-Dist: PyMeasure (>=0.9.0,<0.10.0)
Requires-Dist: PyVISA (>=1.11.3,<2.0.0)
Requires-Dist: PyVISA-py (>=0.5.2,<0.6.0)
Requires-Dist: h5py (>=3.3.0,<4.0.0)
Requires-Dist: matplotlib (>=3.4.2,<4.0.0)
Requires-Dist: nidaqmx (>=0.5.7,<0.6.0)
Requires-Dist: pandas (>=1.3.0,<2.0.0)
Requires-Dist: panel (>=0.11.3,<0.12.0)
Requires-Dist: param (>=1.10.1,<2.0.0)
Requires-Dist: pigpio (>=1.78,<2.0)
Requires-Dist: plotly (>=5.0.0,<6.0.0)
Requires-Dist: pyserial (>=3.5,<4.0)
Requires-Dist: pyusb (>=1.2.0,<2.0.0)
Requires-Dist: scipy (>=1.7.0,<2.0.0)
Requires-Dist: tabulate (>=0.8.9,<0.9.0)
